{
  "supportscredentials":true,
  "alloworigin": [
    "https://3661969-contentpreview.adobeio-static.net",
    "https://aemshowcase4.my.workfront.adobe.com",
    "https://experience.adobe.com"
  ],
  "allowedpaths": [".*"],
  "supportedheaders": [
    "Authorization",
    "Origin",
    "Accept",
    "X-Requested-With",
    "Content-Type",
    "Access-Control-Request-Method",
    "Access-Control-Request-Headers",
    "Access-Control-Allow-Origin"
  ],
  "supportedmethods": [
      "GET",
      "HEAD",
      "POST",
      "PUT",
      "DELETE",
      "PATCH",
      "OPTIONS"
  ],
  "alloworiginregexp": [
    "http://localhost:.*",
    "https://localhost:.*",
    "https://.*\\.adobeio-static\\.net"
  ]
}
